quart_nextcord/__init__.py
quart_nextcord/_http.py
quart_nextcord/client.py
quart_nextcord/configs.py
quart_nextcord/exceptions.py
quart_nextcord/utils.py
quart_nextcord/models/__init__.py
quart_nextcord/models/base.py
quart_nextcord/models/connections.py
quart_nextcord/models/guild.py
quart_nextcord/models/integration.py
quart_nextcord/models/user.py
Quart_Nextcord-2.1.6a1.dist-info/LICENSE
Quart_Nextcord-2.1.6a1.dist-info/METADATA
Quart_Nextcord-2.1.6a1.dist-info/WHEEL
Quart_Nextcord-2.1.6a1.dist-info/top_level.txt
Quart_Nextcord-2.1.6a1.dist-info/RECORD
