Metadata-Version: 2.1
Name: Quart-Nextcord
Version: 2.1.6a1
Summary: Discord OAuth2 extension for Quart.
Home-page: https://github.com/InvalidLenni/Quart-Nextcord
Author: InvalidLenni
License: MIT
Project-URL: Documentation, https://quart-nextcord.rtfd.io/
Project-URL: Issue Tracker, https://github.com/InvalidLenni/Quart-Nextcord/issues/
Requires-Python: >=3.8
License-File: LICENSE
Requires-Dist: quart (==0.17.0)
Requires-Dist: pyjwt (==2.4.0)
Requires-Dist: aiohttp (==3.8.1)
Requires-Dist: oauthlib (==3.2.0)
Requires-Dist: nextcord (==2.0.0a10)
Requires-Dist: cachetools (==5.2.0)
Requires-Dist: setuptools (==62.3.2)
Requires-Dist: Async-OAuthlib (==0.0.9)
